.travis.yml
AUTHORS
ChangeLog
README.rst
requirements.txt
setup.cfg
setup.py
test-requirements.txt
tox.ini
tests/__init__.py
tests/simple_app.py
tests/test_reflect.py
tomb_reflect/__init__.py
tomb_reflect/routemanager.py
tomb_reflect/views.py
tomb_reflect.egg-info/PKG-INFO
tomb_reflect.egg-info/SOURCES.txt
tomb_reflect.egg-info/dependency_links.txt
tomb_reflect.egg-info/not-zip-safe
tomb_reflect.egg-info/pbr.json
tomb_reflect.egg-info/requires.txt
tomb_reflect.egg-info/top_level.txt