Metadata-Version: 1.0
Name: tomb-reflect
Version: 0.0.1
Summary: Add API to introspect routes for your Pyramid web app
Home-page: https://github.com/msabramo/tomb_reflect
Author: Marc Abramowitz
Author-email: johna@gmail.com
License: MIT
Platform: UNKNOWN
